mikmbr/__init__.py
mikmbr/__main__.py
mikmbr/cli.py
mikmbr/config.py
mikmbr/formatters.py
mikmbr/models.py
mikmbr/scanner.py
mikmbr/dependencies/__init__.py
mikmbr/dependencies/osv_client.py
mikmbr/dependencies/parsers.py
mikmbr/dependencies/scanner.py
mikmbr/formatters/sarif.py
mikmbr/rules/__init__.py
mikmbr/rules/bare_except.py
mikmbr/rules/base.py
mikmbr/rules/command_injection.py
mikmbr/rules/dangerous_exec.py
mikmbr/rules/debug_code.py
mikmbr/rules/django_security.py
mikmbr/rules/fastapi_security.py
mikmbr/rules/flask_security.py
mikmbr/rules/hardcoded_secrets.py
mikmbr/rules/insecure_cookie.py
mikmbr/rules/insecure_deserialization.py
mikmbr/rules/insecure_random.py
mikmbr/rules/jwt_security.py
mikmbr/rules/log_injection.py
mikmbr/rules/open_redirect.py
mikmbr/rules/path_traversal.py
mikmbr/rules/regex_dos.py
mikmbr/rules/session_security.py
mikmbr/rules/sql_injection.py
mikmbr/rules/ssl_verification.py
mikmbr/rules/ssrf.py
mikmbr/rules/template_injection.py
mikmbr/rules/timing_attack.py
mikmbr/rules/unsafe_tempfile.py
mikmbr/rules/unsafe_yaml.py
mikmbr/rules/weak_crypto.py
mikmbr/rules/weak_password_hash.py
mikmbr/rules/xxe.py
mikmbr/utils/__init__.py
mikmbr/utils/secret_detection.py
mikmbr/utils/suppression.py
mikmbr-1.8.0.dist-info/licenses/LICENSE
mikmbr-1.8.0.dist-info/METADATA
mikmbr-1.8.0.dist-info/WHEEL
mikmbr-1.8.0.dist-info/entry_points.txt
mikmbr-1.8.0.dist-info/top_level.txt
mikmbr-1.8.0.dist-info/RECORD
